jsonsecrets/__init__.py
jsonsecrets/secret.py
jsonsecrets-1.0.4.dist-info/LICENSE
jsonsecrets-1.0.4.dist-info/METADATA
jsonsecrets-1.0.4.dist-info/WHEEL
jsonsecrets-1.0.4.dist-info/top_level.txt
jsonsecrets-1.0.4.dist-info/RECORD
