Metadata-Version: 2.1
Name: jsonsecrets
Version: 1.0.4
Summary: Load your secrets (API keys etc.) from a JSON file.
Home-page: https://github.com/glowingkitty/JSON-Secrets
Author: Marco
License: UNKNOWN
Platform: UNKNOWN
Classifier: Programming Language :: Python :: 3
Classifier: License :: OSI Approved :: MIT License
Classifier: Operating System :: OS Independent
Requires-Python: >=3.6
Requires-Dist: pyprintplus
